fds/__init__.py
fds/protobuf/__init__.py
fds/protobuf/stach/__init__.py
fds/protobuf/stach/extensions/IStachExtension.py
fds/protobuf/stach/extensions/StachExtensionFactory.py
fds/protobuf/stach/extensions/StachVersion.py
fds/protobuf/stach/extensions/__init__.py
fds/protobuf/stach/extensions/v1/ColumnOrganizedStachExtension.py
fds/protobuf/stach/extensions/v1/ColumnStachExtensionBuilder.py
fds/protobuf/stach/extensions/v1/StachUtilities.py
fds/protobuf/stach/extensions/v1/__init__.py
fds/protobuf/stach/extensions/v2/ColumnOrganizedStachExtension.py
fds/protobuf/stach/extensions/v2/ColumnOrganizedStachUtility.py
fds/protobuf/stach/extensions/v2/ColumnStachExtensionBuilder.py
fds/protobuf/stach/extensions/v2/RowOrganizedStachExtension.py
fds/protobuf/stach/extensions/v2/RowStachExtensionBuilder.py
fds/protobuf/stach/extensions/v2/StachUtilities.py
fds/protobuf/stach/extensions/v2/__init__.py
fds_protobuf_stach_extensions-1.3.3.dist-info/METADATA
fds_protobuf_stach_extensions-1.3.3.dist-info/WHEEL
fds_protobuf_stach_extensions-1.3.3.dist-info/top_level.txt
fds_protobuf_stach_extensions-1.3.3.dist-info/RECORD
