Metadata-Version: 2.4
Name: fds.protobuf.stach.extensions
Version: 1.3.3
Summary: FactSet stach extensions
Home-page: https://github.com/factset/stach-extensions
Author: Analytics API
Author-email: analytics.api.support@factset.com
License: Apache License 2.0
Requires-Python: >=3.9
Requires-Dist: fds.protobuf.stach<2.0.0
Requires-Dist: fds.protobuf.stach.v2<2.0.0
Requires-Dist: pandas<3.0.0
Requires-Dist: numpy<3.0.0
Dynamic: author
Dynamic: author-email
Dynamic: description
Dynamic: home-page
Dynamic: license
Dynamic: requires-dist
Dynamic: requires-python
Dynamic: summary
